vofotensors/__init__.py
vofotensors/abc.py
vofotensors/basic_tensors.py
vofotensors/deviators_2.py
vofotensors/deviators_4.py
vofotensors/fabric_tensors.py
vofotensors/notation.py
vofotensors/numbers.py
vofotensors/substitutions.py
vofotensors/utils.py
vofotensors-1.0.7.dist-info/LICENSE
vofotensors-1.0.7.dist-info/METADATA
vofotensors-1.0.7.dist-info/WHEEL
vofotensors-1.0.7.dist-info/top_level.txt
vofotensors-1.0.7.dist-info/RECORD
