Metadata-Version: 2.1
Name: vofotensors
Version: 1.0.7
Summary: V(ariety)O(f)F(iber)O(rientation)TENSORS contains selected contributions of Bauer JK, Böhlke T. Variety of fiber orientation tensors. Mathematics and Mechanics of Solids. 2022. doi:10.1177/10812865211057602
Home-page: https://github.com/JulianKarlBauer/vofotensors
Author: Julian Karl Bauer
Author-email: juliankarlbauer@gmx.de
Classifier: Programming Language :: Python :: 3
Classifier: Operating System :: OS Independent
License-File: LICENSE
Requires-Dist: numpy
Requires-Dist: sympy
Requires-Dist: pandas
